prestmit/__init__.py
prestmit/client.py
prestmit-0.1.1.dist-info/METADATA
prestmit-0.1.1.dist-info/WHEEL
prestmit-0.1.1.dist-info/top_level.txt
prestmit-0.1.1.dist-info/RECORD
