Metadata-Version: 2.4
Name: prestmit
Version: 0.1.1
Summary: A simple, async-first wrapper for the Prestmit crypto wallet balance API.
Author-email: mineogo <venkatesh10year@gmail.com>
Project-URL: Homepage, https://github.com/mineogo/wallets-wrappper
Project-URL: Bug Tracker, https://github.com/mineogo/wallets-wrapper/issues
Classifier: Programming Language :: Python :: 3
Classifier: License :: OSI Approved :: MIT License
Classifier: Operating System :: OS Independent
Classifier: Intended Audience :: Developers
Classifier: Topic :: Software Development :: Libraries :: Python Modules
Requires-Python: >=3.8
Requires-Dist: aiohttp>=3.8.0
Requires-Dist: requests>=2.20.0
